[
    {
        "type": "collar plain",
        "size": ["s", "m", "l", "xl"],
        "price": "RS.200",
        "image": "edits/collar 1.JPG"
    },
    {
        "type": "collar plain",
        "size": ["s", "m", "l", "xl"],
        "price": "RS.220",
        "image": "edits/collar 2.JPG"
    },
    {
        "type": "collar plain",
        "size": ["s", "m", "l", "xl"],
        "price": "RS.210",
        "image": "edits/collar 3.JPG"
    },
    {
        "type": "collar plain",
        "size": ["s", "m", "l", "xl"],
        "price": "RS.200",
        "image": "edits/collar 4.JPG"
    },
    {
        "type": "collar plain",
        "size": ["s", "m", "l", "xl"],
        "price": "RS.180",
        "image": "edits/collar 5.JPG"
    },
    {
        "type": "collar plain",
        "size": ["s", "m", "l", "xl"],
        "price": "RS.250",
        "image": "edits/collar 6.JPG"
    },
    {
        "type": "collar plain",
        "size": ["s", "m", "l", "xl"],
        "price": "RS.220",
        "image": "edits/collar 7.JPG"
    },
    {
        "type": "collar plain",
        "size": ["s", "m", "l", "xl"],
        "price": "RS.200",
        "image": "edits/collar 8.JPG"
    },
    {
        "type": "collar plain",
        "size": ["s", "m", "l", "xl"],
        "price": "RS.200",
        "image": "edits/collar 9.JPG"
    },
    {
        "type": "collar plain",
        "size": ["s", "m", "l", "xl"],
        "price": "RS.190",
        "image": "edits/collar 10.JPG"
    },
    {
        "type": "collar plain",
        "size": ["s", "m", "l", "xl"],
        "price": "RS.190",
        "image": "edits/collar 11.JPG"
    },
    {
        "type": "collar plain",
        "size": ["s", "m", "l", "xl"],
        "price": "RS.170",
        "image": "edits/collar 12.JPG"
    },
    {
        "type": "collar plain",
        "size": ["s", "m", "l", "xl"],
        "price": "RS.230",
        "image": "edits/collar 13.JPG"
    },
    {
        "type": "collar plain",
        "size": ["s", "m", "l", "xl"],
        "price": "RS.210",
        "image": "edits/collar 14.JPG"
    },
    {
        "type": "collar plain",
        "size": ["s", "m", "l", "xl"],
        "price": "RS.200",
        "image": "edits/collar 15.JPG"
    },
    {
        "type": "collar plain",
        "size": ["s", "m", "l", "xl"],
        "price": "RS.240",
        "image": "edits/collar 16.JPG"
    },
    {
        "type": "collar plain",
        "size": ["s", "m", "l", "xl"],
        "price": "RS.240",
        "image": "edits/collar 17.JPG"
    },
    {
        "type": "collar plain",
        "size": ["s", "m", "l", "xl"],
        "price": "RS.220",
        "image": "edits/collar 18.JPG"
    },
    {
        "type": "collar plain",
        "size": ["s", "m", "l", "xl"],
        "price": "RS.230",
        "image": "edits/collar 19.JPG"
    },
    {
        "type": "collar plain",
        "size": ["s", "m", "l", "xl"],
        "price": "RS.260",
        "image": "edits/collar 20.JPG"
    },
    {
        "type": "collar plain",
        "size": ["s", "m", "l", "xl"],
        "price": "RS.260",
        "image": "edits/collar 21.JPG"
    },
    {
        "type": "collar plain",
        "size": ["s", "m", "l", "xl"],
        "price": "RS.270",
        "image": "edits/collar design1.JPG"
    },
    {
        "type": "collar plain",
        "size": ["s", "m", "l", "xl"],
        "price": "RS.270",
        "image": "edits/collar design2.JPG"
    },
    {
        "type": "collar plain",
        "size": ["s", "m", "l", "xl"],
        "price": "RS.200",
        "image": "edits/collar design3.JPG"
    },
    {
        "type": "collar plain",
        "size": ["s", "m", "l", "xl"],
        "price": "RS.200",
        "image": "edits/collar design4.JPG"
    },
    {
        "type": "collar plain",
        "size": ["s", "m", "l", "xl"],
        "price": "RS.220",
        "image": "edits/collar design5.JPG"
    },
    {
        "type": "collar plain",
        "size": ["s", "m", "l", "xl"],
        "price": "RS.190",
        "image": "edits/collar design6.JPG"
    },
    {
        "type": "collar plain",
        "size": ["s", "m", "l", "xl"],
        "price": "RS.200",
        "image": "edits/collar design7.JPG"
    }
]